fbx_plum/__init__.py
fbx_plum/_version.py
fbx_plum/alias.py
fbx_plum/autoreload.py
fbx_plum/dispatcher.py
fbx_plum/function.py
fbx_plum/method.py
fbx_plum/overload.py
fbx_plum/parametric.py
fbx_plum/promotion.py
fbx_plum/py.typed
fbx_plum/resolver.py
fbx_plum/signature.py
fbx_plum/type.py
fbx_plum/util.py
fenbux_plum_dispatch-0.0.2.dist-info/METADATA
fenbux_plum_dispatch-0.0.2.dist-info/WHEEL
fenbux_plum_dispatch-0.0.2.dist-info/licenses/LICENCE.txt
fenbux_plum_dispatch-0.0.2.dist-info/RECORD
