Metadata-Version: 2.1
Name: fenbux-plum-dispatch
Version: 0.0.2
Summary: Multiple dispatch in Python
Project-URL: repository, https://github.com/JiaYaobo/fenbux-plum
Author-email: Jia Yaobo <januzaj2011@163.com>
License: MIT
License-File: LICENCE.txt
Keywords: multiple dispatch
Classifier: Development Status :: 5 - Production/Stable
Classifier: Programming Language :: Python :: 3
Requires-Python: >=3.8
Requires-Dist: beartype>=0.16.2
Requires-Dist: typing-extensions; python_version <= '3.10'
Provides-Extra: dev
Requires-Dist: black==23.9.0; extra == 'dev'
Requires-Dist: build; extra == 'dev'
Requires-Dist: coveralls; extra == 'dev'
Requires-Dist: ghp-import; extra == 'dev'
Requires-Dist: ipython; extra == 'dev'
Requires-Dist: jupyter-book; extra == 'dev'
Requires-Dist: mypy; extra == 'dev'
Requires-Dist: numpy; extra == 'dev'
Requires-Dist: pre-commit; extra == 'dev'
Requires-Dist: pyright>=1.1.331; extra == 'dev'
Requires-Dist: pytest-cov; extra == 'dev'
Requires-Dist: pytest>=6; extra == 'dev'
Requires-Dist: ruff==0.1.0; extra == 'dev'
Requires-Dist: tox; extra == 'dev'
Requires-Dist: wheel; extra == 'dev'
